boilercv/__init__.py
boilercv/colors.py
boilercv/types.py
boilercv/correlations/__init__.py
boilercv/correlations/meta.toml
boilercv/correlations/models.py
boilercv/correlations/pipes.py
boilercv/correlations/ranges.toml
boilercv/correlations/types.py
boilercv/correlations/beta/__init__.py
boilercv/correlations/beta/equations.toml
boilercv/correlations/beta/expectations.toml
boilercv/correlations/beta/solutions.toml
boilercv/correlations/beta/types.py
boilercv/correlations/nusselt/__init__.py
boilercv/correlations/nusselt/equations.toml
boilercv/correlations/nusselt/expectations.toml
boilercv/correlations/nusselt/solutions.toml
boilercv/correlations/nusselt/types.py
boilercv/data/__init__.py
boilercv/data/frames.py
boilercv/data/models.py
boilercv/data/packing.py
boilercv/dimensionless_params/__init__.py
boilercv/images/__init__.py
boilercv/images/cv.py
boilercv/mappings/__init__.py
boilercv/mappings/types.py
boilercv/morphs/__init__.py
boilercv/morphs/contexts.py
boilercv/morphs/morphs.py
boilercv/morphs/types.py
boilercv-2024.1.3.dist-info/LICENSE
boilercv-2024.1.3.dist-info/WHEEL
boilercv-2024.1.3.dist-info/METADATA
boilercv-2024.1.3.dist-info/RECORD
