Metadata-Version: 2.1
Name: boilercv
Version: 2024.1.3
Summary: Computer vision routines suitable for nucleate pool boiling bubble analysis
Author-email: "Blake Naccarato, Kwang Jin Kim" <blake.naccarato@gmail.com>
Requires-Python: >=3.11
Classifier: License :: OSI Approved :: MIT License
Classifier: Programming Language :: Python :: 3.11
Classifier: Programming Language :: Python :: 3.12
Requires-Dist: matplotlib>=3.7.2
Requires-Dist: numpy>=1.24.4
Requires-Dist: numpydantic>=1.0.0
Requires-Dist: pandas[hdf5,performance]>=2.2.2
Requires-Dist: pillow>=10.3.0
Requires-Dist: pydantic>=2.7.1
Requires-Dist: pytz>=2023.3
Requires-Dist: sympy>=1.12
Requires-Dist: xarray[accel,io,parallel]>=2023.7.0
Requires-Dist: netcdf4>=1.6.5
Requires-Dist: netcdf4!=1.7.1.post1 ; sys_platform == 'linux'
Requires-Dist: opencv-python-headless>=4.9.0.80 ; extra == "cv"
Project-URL: Changes, https://softboiler.github.io/boilercv/changelog.html
Project-URL: Docs, https://softboiler.github.io/boilercv
Project-URL: Home, https://github.com/softboiler/boilercv
Project-URL: Tracker, https://github.com/softboiler/boilercv/issues
Provides-Extra: cv
